LICENSE
MANIFEST.in
README.rst
setup.py
thingdom/__init__.py
thingdom/constants.py
thingdom/httpHelper.py
thingdom/thing.py
thingdom/thingdom.py
thingdom/webService.py
thingdom.egg-info/PKG-INFO
thingdom.egg-info/SOURCES.txt
thingdom.egg-info/dependency_links.txt
thingdom.egg-info/top_level.txt
thingdom/tasks/__init__.py
thingdom/tasks/baseTask.py
thingdom/tasks/feedTask.py
thingdom/tasks/statusTask.py
thingdom/tasks/thingTask.py