Metadata-Version: 1.1
Name: thingdom
Version: 0.1.1
Summary: The official Python wrapper for the Thingdom API
Home-page: https://github.com/thingdomio/thingdom-python
Author: The Thingdom Team
Author-email: echo.team@mts.com
License: MIT
Keywords: mobile development tools
Platform: UNKNOWN
Classifier: Development Status :: 4 - Beta
Classifier: Intended Audience :: Developers
Classifier: Environment :: Web Environment
Classifier: Topic :: Software Development :: Libraries :: Python Modules
Classifier: License :: OSI Approved :: MIT License
Classifier: Programming Language :: Python :: 2.7
